LICENSE
README.md
buildno
requirements.txt
setup.py
windbase/__init__.py
windbase/adminlite.py
windbase/commengine.py
windbase/msgengine.py
windbase/safeengine.py
windbase/securemsg.py
windbase/tools.py
windbase.egg-info/PKG-INFO
windbase.egg-info/SOURCES.txt
windbase.egg-info/dependency_links.txt
windbase.egg-info/entry_points.txt
windbase.egg-info/requires.txt
windbase.egg-info/top_level.txt
windbase/x25519/__init__.py
windbase/x25519/djbec.py