Metadata-Version: 2.1
Name: windbase
Version: 1.0.3.59
Summary: windbase in python
Home-page: https://github.com/gonewind73/wind_util
Author: gonewind.he
Author-email: gonewind.he@gmail.com
Maintainer: gonewind
Maintainer-email: gonewind.he@gmail.com
License: UNKNOWN
Platform: Linux
Platform: Windows
Classifier: Development Status :: 5 - Production/Stable
Classifier: Intended Audience :: Developers
Classifier: License :: OSI Approved :: MIT License
Classifier: Programming Language :: Python :: 3
Classifier: Topic :: Software Development :: Libraries :: Python Modules
Classifier: Topic :: System :: Networking
Requires-Python: >=3
License-File: LICENSE
